mlpro_int_optuna/__init__.py
mlpro_int_optuna/wrappers/__init__.py
mlpro_int_optuna/wrappers/optuna.py
mlpro_int_optuna-1.0.1.dist-info/licenses/LICENSE
mlpro_int_optuna-1.0.1.dist-info/METADATA
mlpro_int_optuna-1.0.1.dist-info/WHEEL
mlpro_int_optuna-1.0.1.dist-info/top_level.txt
mlpro_int_optuna-1.0.1.dist-info/RECORD
