Metadata-Version: 2.4
Name: mlpro_int_optuna
Version: 1.0.1
Summary: MLPro: Integration Optuna
Home-page: https://mlpro-int-optuna.readthedocs.io
Author: MLPro Team
Author-email: mlpro@listen.fh-swf.de
Project-URL: Bug Tracker, https://mlpro-int-optuna.readthedocs.io
Classifier: Programming Language :: Python :: 3
Classifier: License :: OSI Approved :: Apache Software License
Classifier: Operating System :: OS Independent
Requires-Python: >=3.11
License-File: LICENSE
Provides-Extra: full
Requires-Dist: mlpro[full]>=2.1.0; extra == "full"
Requires-Dist: optuna>=3.4.0; extra == "full"
Dynamic: license-file
